kgrv/__init__.py
kgrv/about.py
kgrv/cli_click.py
kgrv-0.1.2.dist-info/licenses/LICENSE
kgrv-0.1.2.dist-info/METADATA
kgrv-0.1.2.dist-info/WHEEL
kgrv-0.1.2.dist-info/entry_points.txt
kgrv-0.1.2.dist-info/top_level.txt
kgrv-0.1.2.dist-info/RECORD
