Metadata-Version: 2.4
Name: kgrv
Version: 0.1.2
Summary: Python пакет для экспериментов и обучения
Home-page: https://github.com/kogriv/kgrv
Author: kogriv
Author-email: kogriv <kogriv@github.com>
Maintainer-email: kogriv <kogrv@github.com>
License: MIT
Project-URL: Homepage, https://github.com/kogriv/kgrv
Project-URL: Repository, https://github.com/kogriv/kgrv.git
Project-URL: Documentation, https://github.com/kogriv/kgrv/tree/master/docs
Project-URL: Bug Reports, https://github.com/kogriv/kgrv/issues
Keywords: python,package,tutorial,learning,example
Classifier: Development Status :: 3 - Alpha
Classifier: Intended Audience :: Developers
Classifier: License :: OSI Approved :: MIT License
Classifier: Operating System :: OS Independent
Classifier: Programming Language :: Python :: 3
Classifier: Programming Language :: Python :: 3.7
Classifier: Programming Language :: Python :: 3.8
Classifier: Programming Language :: Python :: 3.9
Classifier: Programming Language :: Python :: 3.10
Classifier: Programming Language :: Python :: 3.11
Classifier: Topic :: Software Development :: Libraries :: Python Modules
Classifier: Topic :: Utilities
Requires-Python: >=3.7
License-File: LICENSE
Requires-Dist: click>=8.0.0
Requires-Dist: colorama>=0.4.0
Requires-Dist: requests>=2.25.0
Provides-Extra: dev
Requires-Dist: pytest>=6.0.0; extra == "dev"
Requires-Dist: pytest-cov>=2.10.0; extra == "dev"
Requires-Dist: black>=21.0.0; extra == "dev"
Requires-Dist: flake8>=3.8.0; extra == "dev"
Requires-Dist: mypy>=0.910; extra == "dev"
Requires-Dist: twine>=3.4.0; extra == "dev"
Requires-Dist: build>=0.7.0; extra == "dev"
Provides-Extra: docs
Requires-Dist: mkdocs>=1.2.0; extra == "docs"
Requires-Dist: mkdocs-material>=7.0.0; extra == "docs"
Requires-Dist: mkdocstrings>=0.15.0; extra == "docs"
Dynamic: author
Dynamic: home-page
Dynamic: license-file
Dynamic: requires-python
